Rxjs5Ultimate/README.md
Rxjs5Ultimate/__init__.py
Rxjs5Ultimate/__main__.py
Rxjs5Ultimate/file.epub
Rxjs5Ultimate/index.html
Rxjs5Ultimate/css/__init__.py
Rxjs5Ultimate/css/annotations.css
Rxjs5Ultimate/css/main.css
Rxjs5Ultimate/css/normalize.css
Rxjs5Ultimate/css/popup.css
Rxjs5Ultimate/font/__init__.py
Rxjs5Ultimate/font/fontello.eot
Rxjs5Ultimate/font/fontello.svg
Rxjs5Ultimate/font/fontello.ttf
Rxjs5Ultimate/font/fontello.woff
Rxjs5Ultimate/img/__init__.py
Rxjs5Ultimate/img/annotator-glyph-sprite.png
Rxjs5Ultimate/img/annotator-icon-sprite.png
Rxjs5Ultimate/img/apple-touch-icon.png
Rxjs5Ultimate/img/cancelfullscreen.png
Rxjs5Ultimate/img/close.png
Rxjs5Ultimate/img/fullscreen.png
Rxjs5Ultimate/img/loader.gif
Rxjs5Ultimate/img/menu-icon.png
Rxjs5Ultimate/img/save.png
Rxjs5Ultimate/img/saved.png
Rxjs5Ultimate/img/settings-s.png
Rxjs5Ultimate/img/settings.png
Rxjs5Ultimate/img/star.png
Rxjs5Ultimate/js/__init__.py
Rxjs5Ultimate/js/epub.js
Rxjs5Ultimate/js/epub.min.js
Rxjs5Ultimate/js/epub.min.map
Rxjs5Ultimate/js/hooks.min.js
Rxjs5Ultimate/js/hooks.min.map
Rxjs5Ultimate/js/reader.js
Rxjs5Ultimate/js/reader.js.map
Rxjs5Ultimate/js/reader.min.js
Rxjs5Ultimate/js/reader.min.map
Rxjs5Ultimate/js/hooks/__init__.py
Rxjs5Ultimate/js/hooks/extensions/__init__.py
Rxjs5Ultimate/js/hooks/extensions/highlight.js
Rxjs5Ultimate/js/libs/__init__.py
Rxjs5Ultimate/js/libs/jquery.min.js
Rxjs5Ultimate/js/libs/localforage.min.js
Rxjs5Ultimate/js/libs/screenfull.js
Rxjs5Ultimate/js/libs/screenfull.min.js
Rxjs5Ultimate/js/libs/zip.min.js
Rxjs5Ultimate/js/plugins/__init__.py
Rxjs5Ultimate/js/plugins/hypothesis.js
Rxjs5Ultimate/js/plugins/search.js
rxjs_5_ultimate-2024.3.3.0.dist-info/METADATA
rxjs_5_ultimate-2024.3.3.0.dist-info/WHEEL
rxjs_5_ultimate-2024.3.3.0.dist-info/entry_points.txt
rxjs_5_ultimate-2024.3.3.0.dist-info/top_level.txt
rxjs_5_ultimate-2024.3.3.0.dist-info/RECORD
